partitioneer/__init__.py
partitioneer/core.py
partitioneer/manual_parameters.py
partitioneer-0.2.13.dist-info/LICENSE
partitioneer-0.2.13.dist-info/METADATA
partitioneer-0.2.13.dist-info/WHEEL
partitioneer-0.2.13.dist-info/top_level.txt
partitioneer-0.2.13.dist-info/RECORD
