Metadata-Version: 2.1
Name: partitioneer
Version: 0.2.13
Summary: A library for reading and writing partitioned data
Home-page: https://github.com/lachlancahill/partitioneer
Classifier: Programming Language :: Python :: 3
Classifier: License :: OSI Approved :: MIT License
Classifier: Operating System :: OS Independent
Requires-Python: >=3.6
License-File: LICENSE
Requires-Dist: pandas
Requires-Dist: pyarrow
Requires-Dist: tqdm
